medvision_classification-0.2.9.dist-info/licenses/LICENSE
medvision_cls/__init__.py
medvision_cls/cli/__init__.py
medvision_cls/cli/main.py
medvision_cls/datasets/__init__.py
medvision_cls/datasets/medical_datamodule.py
medvision_cls/datasets/medical_dataset.py
medvision_cls/losses/__init__.py
medvision_cls/losses/base_loss.py
medvision_cls/losses/cross_entropy_losses.py
medvision_cls/losses/focal_losses.py
medvision_cls/losses/loss_factory.py
medvision_cls/losses/smoothing_losses.py
medvision_cls/metrics/__init__.py
medvision_cls/metrics/advanced_metrics.py
medvision_cls/metrics/base_metric.py
medvision_cls/metrics/basic_metrics.py
medvision_cls/metrics/metric_collections.py
medvision_cls/metrics/metric_factory.py
medvision_cls/models/__init__.py
medvision_cls/models/base_model.py
medvision_cls/models/convnext.py
medvision_cls/models/densenet.py
medvision_cls/models/efficientnet.py
medvision_cls/models/lightning_module.py
medvision_cls/models/medical_net.py
medvision_cls/models/model_factory.py
medvision_cls/models/resnet.py
medvision_cls/models/resnet3d.py
medvision_cls/models/vit.py
medvision_cls/transforms/__init__.py
medvision_cls/transforms/medical_transforms.py
medvision_cls/utils/__init__.py
medvision_cls/utils/helpers.py
medvision_cls/utils/inference.py
medvision_cls/utils/io.py
medvision_cls/utils/onnx_export.py
medvision_cls/utils/plotting.py
medvision_cls/utils/testing.py
medvision_cls/utils/training.py
medvision_classification-0.2.9.dist-info/METADATA
medvision_classification-0.2.9.dist-info/WHEEL
medvision_classification-0.2.9.dist-info/entry_points.txt
medvision_classification-0.2.9.dist-info/top_level.txt
medvision_classification-0.2.9.dist-info/RECORD
