Metadata-Version: 2.4
Name: medvision-classification
Version: 0.2.9
Summary: A comprehensive PyTorch Lightning framework for medical image classification with support for 2D/3D images
Author-email: weizhipeng <weizhipeng@shu.edu.cn>
License: MIT
Project-URL: Homepage, https://github.com/Hi-Zhipeng/MedVision-classification
Project-URL: Repository, https://github.com/Hi-Zhipeng/MedVision-classification
Project-URL: Documentation, https://github.com/Hi-Zhipeng/MedVision-classification#readme
Project-URL: Bug Tracker, https://github.com/Hi-Zhipeng/MedVision-classification/issues
Keywords: medical imaging,classification,pytorch,lightning,deep learning
Classifier: Development Status :: 3 - Alpha
Classifier: Intended Audience :: Developers
Classifier: Intended Audience :: Science/Research
Classifier: License :: OSI Approved :: MIT License
Classifier: Operating System :: OS Independent
Classifier: Programming Language :: Python :: 3
Classifier: Programming Language :: Python :: 3.8
Classifier: Programming Language :: Python :: 3.9
Classifier: Programming Language :: Python :: 3.10
Classifier: Programming Language :: Python :: 3.11
Classifier: Topic :: Scientific/Engineering :: Artificial Intelligence
Classifier: Topic :: Scientific/Engineering :: Medical Science Apps.
Requires-Python: >=3.8
License-File: LICENSE
Requires-Dist: torch>=2.0.0
Requires-Dist: torchvision>=0.15.0
Requires-Dist: pytorch-lightning>=2.0.0
Requires-Dist: lightning>=2.0.0
Requires-Dist: numpy>=1.21.0
Requires-Dist: pyyaml>=6.0
Requires-Dist: tqdm>=4.64.0
Requires-Dist: click>=8.0.0
Requires-Dist: pillow>=9.0.0
Requires-Dist: scikit-image>=0.19.0
Requires-Dist: pandas>=1.4.0
Requires-Dist: nibabel>=3.2.0
Requires-Dist: SimpleITK>=2.2.0
Requires-Dist: pydicom>=2.3.0
Requires-Dist: monai>=1.3.0
Requires-Dist: opencv-python>=4.7.0
Requires-Dist: albumentations>=1.3.0
Requires-Dist: matplotlib>=3.6.0
Requires-Dist: seaborn>=0.12.0
Requires-Dist: tensorboard>=2.10.0
Requires-Dist: scikit-learn>=1.1.0
Requires-Dist: scipy>=1.9.0
Requires-Dist: torchmetrics>=0.11.0
Requires-Dist: timm>=0.9.0
Requires-Dist: efficientnet-pytorch>=0.7.0
Requires-Dist: hydra-core>=1.3.0
Requires-Dist: omegaconf>=2.3.0
Requires-Dist: rich>=13.0.0
Provides-Extra: dev
Requires-Dist: pytest>=7.0.0; extra == "dev"
Requires-Dist: pytest-cov>=4.0.0; extra == "dev"
Requires-Dist: black>=22.0.0; extra == "dev"
Requires-Dist: flake8>=5.0.0; extra == "dev"
Requires-Dist: isort>=5.10.0; extra == "dev"
Requires-Dist: mypy>=0.991; extra == "dev"
Requires-Dist: pre-commit>=2.20.0; extra == "dev"
Requires-Dist: jupyter>=1.0.0; extra == "dev"
Requires-Dist: ipykernel>=6.0.0; extra == "dev"
Provides-Extra: docs
Requires-Dist: sphinx>=5.0.0; extra == "docs"
Requires-Dist: sphinx-rtd-theme>=1.0.0; extra == "docs"
Requires-Dist: myst-parser>=0.18.0; extra == "docs"
Provides-Extra: all
Requires-Dist: wandb>=0.15.0; extra == "all"
Requires-Dist: onnx>=1.12.0; extra == "all"
Requires-Dist: onnxruntime>=1.12.0; extra == "all"
Dynamic: license-file
